README.md
setup.cfg
setup.py
karajan/__init__.py
karajan/conductor.py
karajan/config.py
karajan/dependencies.py
karajan/engines.py
karajan/exceptions.py
karajan/model.py
karajan/operators.py
karajan/transformations.py
karajan/validations.py
karajan.egg-info/PKG-INFO
karajan.egg-info/SOURCES.txt
karajan.egg-info/dependency_links.txt
karajan.egg-info/requires.txt
karajan.egg-info/top_level.txt
karajan/bin/__init__.py
karajan/bin/cli.py
karajan/bin/karajan